mobiletestorchestrator/__init__.py
mobiletestorchestrator/application.py
mobiletestorchestrator/device.py
mobiletestorchestrator/device_interactions.py
mobiletestorchestrator/device_log.py
mobiletestorchestrator/device_networking.py
mobiletestorchestrator/device_pool.py
mobiletestorchestrator/device_queue.py
mobiletestorchestrator/device_storage.py
mobiletestorchestrator/emulators.py
mobiletestorchestrator/main.py
mobiletestorchestrator/parsing.py
mobiletestorchestrator/reporting.py
mobiletestorchestrator/testprep.py
mobiletestorchestrator/timing.py
mobiletestorchestrator/worker.py
mobiletestorchestrator/resources/apks/TestButlerLive.apk
mobiletestorchestrator/resources/apks/__init__.py
mobiletestorchestrator/resources/sdkmanager/bootstrap.zip
mobiletestorchestrator/runners/__init__.py
mobiletestorchestrator/runners/upgradetestrunner.py
mobiletestorchestrator/tooling/__init__.py
mobiletestorchestrator/tooling/bundle.py
mobiletestorchestrator/tooling/sdkmanager.py
mobiletestorchestrator-3.0.1.dist-info/METADATA
mobiletestorchestrator-3.0.1.dist-info/WHEEL
mobiletestorchestrator-3.0.1.dist-info/entry_points.txt
mobiletestorchestrator-3.0.1.dist-info/top_level.txt
mobiletestorchestrator-3.0.1.dist-info/RECORD
