Metadata-Version: 2.1
Name: mobiletestorchestrator
Version: 3.0.1
Summary: UNKNOWN
Home-page: UNKNOWN
Author: UNKNOWN
Author-email: UNKNOWN
License: UNKNOWN
Platform: UNKNOWN
Requires-Dist: apk-bitminer (>=1.1.0)
